plugin_module.py
my_nellie_plugin-0.1.4.dist-info/LICENSE
my_nellie_plugin-0.1.4.dist-info/METADATA
my_nellie_plugin-0.1.4.dist-info/WHEEL
my_nellie_plugin-0.1.4.dist-info/entry_points.txt
my_nellie_plugin-0.1.4.dist-info/top_level.txt
my_nellie_plugin-0.1.4.dist-info/RECORD
