Metadata-Version: 2.1
Name: my-nellie-plugin
Version: 0.1.4
Summary: A plugin for Nellie that does XYZ
Home-page: https://github.com/yourusername/my-nellie-plugin
Author: Your Name
Author-email: your.email@example.com
Classifier: Programming Language :: Python :: 3
Classifier: License :: OSI Approved :: MIT License
Classifier: Operating System :: OS Independent
Requires-Python: >=3.6
License-File: LICENSE
Requires-Dist: nellie
Requires-Dist: numpy
